cyanprintsdk/__init__.py
cyanprintsdk/api/__init__.py
cyanprintsdk/api/base_model.py
cyanprintsdk/api/core/__init__.py
cyanprintsdk/api/core/answer_req.py
cyanprintsdk/api/core/answer_res.py
cyanprintsdk/api/core/core_mapper.py
cyanprintsdk/api/core/cyan_req.py
cyanprintsdk/api/core/cyan_res.py
cyanprintsdk/api/core/question_res.py
cyanprintsdk/api/plugin/__init__.py
cyanprintsdk/api/plugin/fn.py
cyanprintsdk/api/plugin/mapper.py
cyanprintsdk/api/plugin/req.py
cyanprintsdk/api/plugin/res.py
cyanprintsdk/api/processor/__init__.py
cyanprintsdk/api/processor/fn.py
cyanprintsdk/api/processor/mapper.py
cyanprintsdk/api/processor/req.py
cyanprintsdk/api/processor/res.py
cyanprintsdk/api/template/__init__.py
cyanprintsdk/api/template/fn.py
cyanprintsdk/api/template/mapper.py
cyanprintsdk/api/template/req.py
cyanprintsdk/api/template/res.py
cyanprintsdk/domain/__init__.py
cyanprintsdk/domain/core/__init__.py
cyanprintsdk/domain/core/answer.py
cyanprintsdk/domain/core/cyan.py
cyanprintsdk/domain/core/cyan_script.py
cyanprintsdk/domain/core/cyan_script_model.py
cyanprintsdk/domain/core/deterministic.py
cyanprintsdk/domain/core/fs/__init__.py
cyanprintsdk/domain/core/fs/cyan_fs_helper.py
cyanprintsdk/domain/core/fs/virtual_file.py
cyanprintsdk/domain/core/inquirer.py
cyanprintsdk/domain/core/question.py
cyanprintsdk/domain/plugin/__init__.py
cyanprintsdk/domain/plugin/input.py
cyanprintsdk/domain/plugin/output.py
cyanprintsdk/domain/plugin/service.py
cyanprintsdk/domain/processor/__init__.py
cyanprintsdk/domain/processor/input.py
cyanprintsdk/domain/processor/output.py
cyanprintsdk/domain/processor/service.py
cyanprintsdk/domain/service/__init__.py
cyanprintsdk/domain/service/out_of_answer_error.py
cyanprintsdk/domain/service/stateless_determinism.py
cyanprintsdk/domain/service/stateless_inquirer.py
cyanprintsdk/domain/template/__init__.py
cyanprintsdk/domain/template/input.py
cyanprintsdk/domain/template/output.py
cyanprintsdk/domain/template/service.py
cyanprintsdk/main.py
cyanprintsdk-2.0.1.dist-info/METADATA
cyanprintsdk-2.0.1.dist-info/WHEEL
cyanprintsdk-2.0.1.dist-info/RECORD
