Metadata-Version: 2.1
Name: cyanprintsdk
Version: 2.0.1
Summary: CyanPrint SDK for building templates, extensions, plugins or processors
Home-page: https://docs.cyanprint.dev
License: MIT
Author: Ernest Ng
Author-email: ernest@atomi.cloud
Requires-Python: >=3.11,<4.0
Classifier: License :: OSI Approved :: MIT License
Classifier: Programming Language :: Python :: 3
Classifier: Programming Language :: Python :: 3.11
Classifier: Programming Language :: Python :: 3.12
Classifier: Programming Language :: Python :: 3.13
Requires-Dist: aiohttp (>=3.8.6,<4.0.0)
Requires-Dist: pydantic (>=2.4.2,<3.0.0)
Project-URL: Repository, https://github.com/AtomiCloud/sulfone.helium
